ai/__init__.py
ai/_version.py
ai/ai.py
ai/api_utils.py
ai/knowledgebase_utils.py
ai/metrics.py
ai/q_utils.py
ai/request_manager.py
ai/metalearning/__init__.py
ai/metalearning/dataset_describe.py
ai/metalearning/export_to_mongo.py
ai/metalearning/get_metafeatures.py
ai/metalearning/make_meta_ml_dataset.py
ai/recommender/__init__.py
ai/recommender/average_recommender.py
ai/recommender/base.py
ai/recommender/knn_meta_recommender.py
ai/recommender/random_recommender.py
ai/recommender/surprise_recommenders.py
ai/sklearn/__init__.py
ai/sklearn/pennai_sklearn.py
ai/sklearn/config/__init__.py
ai/sklearn/config/classifiers.py
ai/sklearn/config/regressors.py
pennai/__init__.py
pennai/_version.py
pennai/ai.py
pennai/api_utils.py
pennai/knowledgebase_utils.py
pennai/metrics.py
pennai/q_utils.py
pennai/request_manager.py
pennai/metalearning/__init__.py
pennai/metalearning/dataset_describe.py
pennai/metalearning/export_to_mongo.py
pennai/metalearning/get_metafeatures.py
pennai/metalearning/make_meta_ml_dataset.py
pennai/recommender/__init__.py
pennai/recommender/average_recommender.py
pennai/recommender/base.py
pennai/recommender/knn_meta_recommender.py
pennai/recommender/random_recommender.py
pennai/recommender/surprise_recommenders.py
pennai/sklearn/__init__.py
pennai/sklearn/pennai_sklearn.py
pennai/sklearn/config/__init__.py
pennai/sklearn/config/classifiers.py
pennai/sklearn/config/regressors.py
pennaipy/__init__.py
pennaipy/_version.py
pennaipy/ai.py
pennaipy/api_utils.py
pennaipy/knowledgebase_utils.py
pennaipy/metrics.py
pennaipy/q_utils.py
pennaipy/request_manager.py
pennaipy/metalearning/__init__.py
pennaipy/metalearning/dataset_describe.py
pennaipy/metalearning/export_to_mongo.py
pennaipy/metalearning/get_metafeatures.py
pennaipy/metalearning/make_meta_ml_dataset.py
pennaipy/recommender/__init__.py
pennaipy/recommender/average_recommender.py
pennaipy/recommender/base.py
pennaipy/recommender/knn_meta_recommender.py
pennaipy/recommender/random_recommender.py
pennaipy-0.17a3.dist-info/LICENSE
pennaipy-0.17a3.dist-info/METADATA
pennaipy-0.17a3.dist-info/WHEEL
pennaipy-0.17a3.dist-info/top_level.txt
pennaipy-0.17a3.dist-info/zip-safe
pennaipy-0.17a3.dist-info/RECORD
